oardocker/__init__.py
oardocker/actions.py
oardocker/cli.py
oardocker/client.py
oardocker/compat.py
oardocker/container.py
oardocker/context.py
oardocker/state.py
oardocker/utils.py
oardocker/commands/__init__.py
oardocker/commands/cmd_build.py
oardocker/commands/cmd_clean.py
oardocker/commands/cmd_connect.py
oardocker/commands/cmd_destroy.py
oardocker/commands/cmd_exec.py
oardocker/commands/cmd_init.py
oardocker/commands/cmd_install.py
oardocker/commands/cmd_logs.py
oardocker/commands/cmd_reset.py
oardocker/commands/cmd_start.py
oardocker/commands/cmd_status.py
oardocker/commands/cmd_stop.py
oardocker/templates/bullseye/manifest.json
oardocker/templates/bullseye/images/base/Dockerfile
oardocker/templates/bullseye/images/frontend/Dockerfile
oardocker/templates/bullseye/images/frontend/install_oar.sh
oardocker/templates/bullseye/images/node/Dockerfile
oardocker/templates/bullseye/images/rsyslog/Dockerfile
oardocker/templates/bullseye/images/server/Dockerfile
oardocker/templates/bullseye/images/server/systemd/oardocker-postgresql@13-main.service
oardocker/templates/buster/manifest.json
oardocker/templates/buster/images/base/Dockerfile
oardocker/templates/buster/images/frontend/Dockerfile
oardocker/templates/buster/images/frontend/install_oar.sh
oardocker/templates/buster/images/node/Dockerfile
oardocker/templates/buster/images/rsyslog/Dockerfile
oardocker/templates/buster/images/server/Dockerfile
oardocker/templates/buster/images/server/systemd/oardocker-postgresql@11-main.service
oardocker/templates/cigri/README.md
oardocker/templates/cigri/manifest.json
oardocker/templates/cigri/images/frontend/Dockerfile
oardocker/templates/cigri/images/frontend/init_cigri.sh
oardocker/templates/cigri/images/frontend/install_cigri.sh
oardocker/templates/cigri/images/frontend/start_cigri.sh
oardocker/templates/cigri/images/node/Dockerfile
oardocker/templates/cigri/images/node/install_cigri.sh
oardocker/templates/cigri/images/rsyslog/Dockerfile
oar_docker-1.6.3.dist-info/METADATA
oar_docker-1.6.3.dist-info/WHEEL
oar_docker-1.6.3.dist-info/entry_points.txt
oar_docker-1.6.3.dist-info/top_level.txt
oar_docker-1.6.3.dist-info/RECORD
