Metadata-Version: 2.1
Name: oar-docker
Version: 1.6.3
Summary: Manage a small OAR developpement cluster with docker.
Home-page: https://oar.imag.fr/wiki:oar-docker
Author: Salem Harrache
Author-email: salem@harrache.info
License: UNKNOWN
Platform: UNKNOWN
Classifier: License :: OSI Approved :: BSD License
Classifier: Programming Language :: Python
Classifier: Programming Language :: Python :: 3
Requires-Dist: Click
Requires-Dist: docker
Requires-Dist: sh
Requires-Dist: tabulate
Requires-Dist: arrow
